Workbook
Name anos_invest: APP!$C$14
Name aporte: APP!$C$13
Name rend_carteira: APP!$C$9
Name sug_invest: APP!$C$10
Name taxa_mensal: APP!$C$15

Sheet APP
C2: DIO INVEST
B7: CONFIGURAÇÕES | F7: PERFIL | G7: Moderado
B8: Salário | C8: 2000 | F8: VALOR A SER INVESTIDO POR MÊS | G8: =aporte -> 200
B9: Redimento carteira | C9: 0.006
B10: Sugestão investimento | C10: =C8*30% -> 600 | F10: TIPO DE FII | G10: Percentual Sugerido | H10: Valores
F11: PAPEL | G11: =VLOOKUP($G$7&"-"&F11,Suporte!B:E,4,FALSE) -> 0.32 | H11: =G11*$G$8 -> 64
B12: INVESTIMENTO MENSAL | F12: TIJOLO | G12: =VLOOKUP($G$7&"-"&F12,Suporte!B:E,4,FALSE) -> 0.35 | H12: =G12*$G$8 -> 70
B13: Quanto investir por mês? | C13: 200 | F13: HÍBRIDOS | G13: =VLOOKUP($G$7&"-"&F13,Suporte!B:E,4,FALSE) -> 0.08 | H13: =G13*$G$8 -> 16
B14: Por quantos anos? | C14: 5 | F14: FOFs | G14: =VLOOKUP($G$7&"-"&F14,Suporte!B:E,4,FALSE) -> 0.05 | H14: =G14*$G$8 -> 10
B15: Taxa de rendimento mensal? | C15: 0.0108 | F15: DESENVOLVIMENTO | G15: =VLOOKUP($G$7&"-"&F15,Suporte!B:E,4,FALSE) -> 0.1 | H15: =G15*$G$8 -> 20
B16: Patrimônio acumulado? | C16: =FV(C15,C14*12,C13*-1) -> 16760.804 | F16: HOTELARIAS | G16: =VLOOKUP($G$7&"-"&F16,Suporte!B:E,4,FALSE) -> 0.1 | H16: =G16*$G$8 -> 20
B17: Dividendos Mensais? | C17: =C16*1% -> 167.60804 | G17: =SUM(G11:G16) -> 1 | H17: =SUM(H11:H16) -> 200
B19: CENÁRIOS
B20: Anos | C20: Valor | D20: Dividendos
B21: 2 | C21: =FV($C$15,B21*12,$C$13*-1) -> 5446.1727 | D21: =C21*rend_carteira -> 32.677036
B22: 5 | C22: =FV($C$15,B22*12,$C$13*-1) -> 16760.804 | D22: =C22*rend_carteira -> 100.56482
B23: 10 | C23: =FV($C$15,B23*12,$C$13*-1) -> 48691.533 | D23: =C23*rend_carteira -> 292.1492
B24: 20 | C24: =FV($C$15,B24*12,$C$13*-1) -> 225409.8 | D24: =C24*rend_carteira -> 1352.4588
B25: 30 | C25: =FV($C$15,B25*12,$C$13*-1) -> 866780.96 | D25: =C25*rend_carteira -> 5200.6858

Sheet Suporte
B3: CHAVE | C3: PERFIL | D3: TIPO DE FII | E3: %
B4: Conservador-PAPEL | C4: Conservador | D4: PAPEL | E4: 0.3
B5: Conservador-TIJOLO | C5: Conservador | D5: TIJOLO | E5: 0.5
B6: Conservador-HÍBRIDOS | C6: Conservador | D6: HÍBRIDOS | E6: 0.1
B7: Conservador-FOFs | C7: Conservador | D7: FOFs | E7: 0.1
B8: Conservador-DESENVOLVIMENTO | C8: Conservador | D8: DESENVOLVIMENTO | E8: 0
B9: Conservador-HOTELARIAS | C9: Conservador | D9: HOTELARIAS | E9: 0
B10: Moderado-PAPEL | C10: Moderado | D10: PAPEL | E10: 0.32
B11: Moderado-TIJOLO | C11: Moderado | D11: TIJOLO | E11: 0.35
B12: Moderado-HÍBRIDOS | C12: Moderado | D12: HÍBRIDOS | E12: 0.08
B13: Moderado-FOFs | C13: Moderado | D13: FOFs | E13: 0.05
B14: Moderado-DESENVOLVIMENTO | C14: Moderado | D14: DESENVOLVIMENTO | E14: 0.1
B15: Moderado-HOTELARIAS | C15: Moderado | D15: HOTELARIAS | E15: 0.1
... B21: Agressivo-HOTELARIAS | C21: Agressivo | D21: HOTELARIAS | E21: 0.1
